domain_manager/__init__.py
domain_manager/_version.py
domain_manager/config.py
domain_manager/config.yaml
domain_manager/logger.py
domain_manager/main.py
domain_manager/updater.py
domain_manager/templates/nginx_config_template.conf
domain_manager/utils/__init__.py
domain_manager/utils/backup.py
domain_manager/utils/data_files.py
domain_manager/utils/display.py
domain_manager/utils/display_v2.py
domain_manager/utils/domain.py
domain_manager/utils/permissions.py
domain_manager/utils/validation.py
NGINXDomainManager-2.5.12.post1.dev0.dist-info/METADATA
NGINXDomainManager-2.5.12.post1.dev0.dist-info/WHEEL
NGINXDomainManager-2.5.12.post1.dev0.dist-info/entry_points.txt
NGINXDomainManager-2.5.12.post1.dev0.dist-info/top_level.txt
NGINXDomainManager-2.5.12.post1.dev0.dist-info/RECORD
