Metadata-Version: 2.1
Name: NGINXDomainManager
Version: 2.5.12.post1.dev0
Summary: A tool to manage NGINX domains
Author-email: Your Name <your.email@example.com>
License: MIT License
Project-URL: Homepage, https://github.com/Bof98/NGINXDomainManager
Project-URL: Issues, https://github.com/Bof98/NGINXDomainManager/issues
Requires-Python: >=3.7
Requires-Dist: PyYAML>=6.0.2
Requires-Dist: colorama>=0.4.6
Requires-Dist: requests>=2.31.0
Requires-Dist: packaging>=24.1
